modded_pytonapi/__init__.py
modded_pytonapi/exceptions.py
modded_pytonapi/utils.py
modded_pytonapi/async_tonapi/__init__.py
modded_pytonapi/async_tonapi/client.py
modded_pytonapi/async_tonapi/methods/__init__.py
modded_pytonapi/async_tonapi/methods/accounts.py
modded_pytonapi/async_tonapi/methods/blockchain.py
modded_pytonapi/async_tonapi/methods/dns.py
modded_pytonapi/async_tonapi/methods/events.py
modded_pytonapi/async_tonapi/methods/jettons.py
modded_pytonapi/async_tonapi/methods/nft.py
modded_pytonapi/async_tonapi/methods/rates.py
modded_pytonapi/async_tonapi/methods/staking.py
modded_pytonapi/async_tonapi/methods/storage.py
modded_pytonapi/async_tonapi/methods/traces.py
modded_pytonapi/schema/__init__.py
modded_pytonapi/schema/_address.py
modded_pytonapi/schema/_balance.py
modded_pytonapi/schema/accounts.py
modded_pytonapi/schema/blockchain.py
modded_pytonapi/schema/dns.py
modded_pytonapi/schema/domains.py
modded_pytonapi/schema/events.py
modded_pytonapi/schema/jettons.py
modded_pytonapi/schema/nft.py
modded_pytonapi/schema/rates.py
modded_pytonapi/schema/staking.py
modded_pytonapi/schema/storage.py
modded_pytonapi/schema/traces.py
modded_pytonapi/tonapi/__init__.py
modded_pytonapi/tonapi/client.py
modded_pytonapi/tonapi/methods/__init__.py
modded_pytonapi/tonapi/methods/accounts.py
modded_pytonapi/tonapi/methods/blockchain.py
modded_pytonapi/tonapi/methods/dns.py
modded_pytonapi/tonapi/methods/events.py
modded_pytonapi/tonapi/methods/jettons.py
modded_pytonapi/tonapi/methods/nft.py
modded_pytonapi/tonapi/methods/rates.py
modded_pytonapi/tonapi/methods/staking.py
modded_pytonapi/tonapi/methods/storage.py
modded_pytonapi/tonapi/methods/traces.py
pytonapi/__init__.py
pytonapi/exceptions.py
pytonapi/utils.py
pytonapi/async_tonapi/__init__.py
pytonapi/async_tonapi/client.py
pytonapi/async_tonapi/methods/__init__.py
pytonapi/async_tonapi/methods/accounts.py
pytonapi/async_tonapi/methods/blockchain.py
pytonapi/async_tonapi/methods/dns.py
modded_pytonapi-0.0.6.dist-info/LICENSE
modded_pytonapi-0.0.6.dist-info/METADATA
modded_pytonapi-0.0.6.dist-info/WHEEL
modded_pytonapi-0.0.6.dist-info/top_level.txt
modded_pytonapi-0.0.6.dist-info/RECORD
