Metadata-Version: 2.1
Name: modded_pytonapi
Version: 0.0.6
Summary: Separate implementation of pytonapi
Home-page: https://github.com/spencerwilf/pytonapi
Author: spencerwilf
Classifier: Programming Language :: Python :: 3.7
Classifier: Programming Language :: Python :: 3.8
Classifier: Programming Language :: Python :: 3.9
Classifier: Programming Language :: Python :: 3.10
Classifier: Programming Language :: Python :: 3.11
Classifier: Programming Language :: Python :: 3.12
Classifier: License :: OSI Approved :: MIT License
Classifier: Operating System :: OS Independent
License-File: LICENSE
Requires-Dist: httpx>=0.26.0
Requires-Dist: websockets>=12.0
Requires-Dist: pydantic==2.*
